probcalc/__init__.py
probcalc/distribution_classes.py
probcalc/distributions.py
probcalc/py.typed
probcalc/utility.py
probcalc-0.5.0.dist-info/COPYING
probcalc-0.5.0.dist-info/METADATA
probcalc-0.5.0.dist-info/WHEEL
probcalc-0.5.0.dist-info/top_level.txt
probcalc-0.5.0.dist-info/RECORD
